CHANGES.md
DEVELOP.md
LICENSE
MANIFEST.in
README.md
setup.py
demos/ant.core/01-reset.py
demos/ant.core/02-capabilities.py
demos/ant.core/03-basicchannel.py
demos/ant.core/04-processevents.py
demos/ant.core/05-rawmessage.py
demos/ant.core/06-rawmessage2.py
demos/ant.core/07-rawmessage3.py
demos/ant.core/08-rawmessage4.py
demos/ant.core/09-logreader.py
demos/ant.core/config.py
src/ant/__init__.py
src/ant.egg-info/PKG-INFO
src/ant.egg-info/SOURCES.txt
src/ant.egg-info/dependency_links.txt
src/ant.egg-info/requires.txt
src/ant.egg-info/top_level.txt
src/ant/core/__init__.py
src/ant/core/constants.py
src/ant/core/driver.py
src/ant/core/event.py
src/ant/core/exceptions.py
src/ant/core/log.py
src/ant/core/message.py
src/ant/core/node.py
src/ant/core/tests/driver_tests.py
src/ant/core/tests/event_tests.py
src/ant/core/tests/log_tests.py
src/ant/core/tests/message_tests.py
src/ant/core/tests/node_tests.py
src/ant/fs/__init__.py
src/ant/plus/__init__.py