Metadata-Version: 1.0
Name: ant
Version: 0.1.0
Summary: Python implementation of the ANT, ANT+, and ANT-FS protocols (http://www.thisisant.com/).
Home-page: http://www.github.com/mvillalba/python-ant
Author: Martín Raúl Villalba
Author-email: martin@martinvillalba.com
License: MIT
Platform: UNKNOWN
Classifier: Development Status :: 2 - Pre-Alpha
Classifier: Intended Audience :: Developers
Classifier: License :: OSI Approved :: MIT License
Classifier: Operating System :: OS Independent
Classifier: Programming Language :: Python
Classifier: Programming Language :: Python :: 2.6
Classifier: Programming Language :: Python :: 2.7
Classifier: Topic :: Communications
Classifier: Topic :: Communications :: File Sharing
Classifier: Topic :: Software Development :: Libraries :: Python Modules
